Reg.v
module Reg (
    input [23:0] in,
    output reg [23:0] out,
    input write,
    input clk
);
    reg [23:0] Register;
    initial 
        Register = 0; 
    always @(posedge clk) begin
        if(write)
        Register <= in;   
    end
    always @(*)
    out <= Register;
endmodule

Mux.v
module Mux2x1 (
    input sel,
    input [23:0] a,
    input[23:0] b,
    output reg [23:0] out
);
  always @(*) begin
    if (sel)
      out <= b;
    else 
      out <= a;
  end 
endmodule
module Mux4x1 (
    input [1:0] sel,
    input [23:0] a,
    input[23:0] b,
    input[23:0] c,
    input [23:0] d,
    output reg [23:0] out
);
  always @(*) begin
    case (sel)
      2'b00:out<=a;
      2'b01:out<=b;
      2'b10:out<=c;
      2'b11:out<=d;
    endcase
  end
endmodule

ALU.v
module ALU (
    input [23:0] A,B,
    input [4:0] OP,
    output reg zeroFlag,
    output reg [23:0] Result
);
    initial Result = 0;
    reg [23:0] temp;
    always @(OP or A or B) begin
        case(OP)
        5'b00000, 5'b00111:
        temp = A&B;
        5'b00001:
        begin
            if (A > B) begin
            temp = A;
        end
        else begin
            temp = B;
        end
        end
        5'b00011, 5'b00010,5'b01000, 5'b01001, 5'b01010,5'b01001:
            temp = A + B;
        5'b00100, 5'b01011 ,5'b01011:
            temp = A-B;
        5'b00101:
            temp = A >= B;
        5'b01111:
        begin

        end

        endcase
        Result <= temp;
        zeroFlag <= temp == 0;
    end
endmodule

SignExtend.v
module SignExtend#(parameter bits = 17)(
    input [bits-1:0] in,
    input ExtOp,
    output reg [23:0] out
);
    always @(*) begin
        out[bits-1:0] <= in[bits-1:0];
        out[23:bits] <= (ExtOp&in[bits-1])*(2**(24-bits));
    end
endmodule

RegFile.v
module RegisterFile (
    input [2:0] Rdata1,
    input [2:0] Rdata2,
    input [2:0] WriteReg,
    input [23:0] Wdata,
    output reg [23:0] Outdata1,
    output reg [23:0] Outdata2,
    input RegWrite,
    input clk
);
    reg[23:0] RegFile[8];
    integer i;
    initial begin
        for( i=0;i<8;i++)
            begin
                RegFile[i] = 0; 
                end
    end
    always @(posedge clk) begin
        if(RegWrite & WriteReg != 0)
            RegFile[WriteReg] <= Wdata;
    end
    always @(*) begin
     Outdata1 <= RegFile[Rdata1];
    end
    always @(*) begin
        Outdata2 <= RegFile[Rdata2];
    end
endmodule

Memory.v
module Memory (
    input [23:0] Address,
    input [23:0] DataIn,
    output [23:0] DataOut,
    input MemW,
    input MemR,
    input clk
);
reg[23:0] Mem[2**24];
    integer i;
    initial begin
        for( i=0;i<2**24;i++)
            begin
                Mem[i] = 0; 
                end
    end
    always @(posedge clk) begin
        if(MemW)
            Mem[Address] <= DataIn;
    end
    assign DataOut = MemR?Mem[Address]:0;  
endmodule

Adder.v
module Adder#(parameter bits = 23) (
    A,
    B,
    out
);
input [bits:0] A;
input [23:0] B;
output [23:0] out;
assign out = A+B;
endmodule

writeControl.v
module writeControl (
    input [4:0] Op,
    input zeroFlag,
    output reg RegWrite,
    output reg MemWrite,
    output reg PCWriteCond,
    input clk
);
    
    always @(posedge clk) begin
            #1
            if (Op == 5'b01001 || Op ==5'b00010)
            begin
                repeat (3)@(posedge clk);
                PCWriteCond <= 1;
                @(posedge clk);
                PCWriteCond <= 0;
            end
            else if (Op == 5'b01010)
            begin //SW
                repeat (2)@(posedge clk);
                PCWriteCond <= 1;
                @(posedge clk);
                PCWriteCond <= 0;
            end
            else if (Op ==5'b01011)//BEQ
            begin
                @(posedge clk);
                PCWriteCond <= 1;
                @(posedge clk);
                PCWriteCond <= 0;
            end
            else if (Op ==5'b00110)
            begin // JR
                @(posedge clk);
                PCWriteCond <=1;
                @(posedge clk);
                PCWriteCond <= 0;
            end
            else if (Op ==5'b00000 || Op ==5'b00001  || Op ==5'b00011 || Op ==5'b00100 || Op ==5'b00101 || Op ==5'b01000 || Op ==5'b00111)
            begin
                repeat (2)@(posedge clk);
                PCWriteCond <= 1;
                @(posedge clk);
                PCWriteCond <= 0;
            end
            else if (Op ==5'b01101)
                begin // JAL
                @(posedge clk);
                PCWriteCond <= 1;
                @(posedge clk);
                PCWriteCond <= 0;
                end
            else if (Op ==5'b01110)
            begin // LUI
                @(posedge clk);
                PCWriteCond <= 1;
                @(posedge clk);
                PCWriteCond <= 0;
            end
            else if (Op ==5'b00101)
            begin // CMP
                @(posedge clk);
                PCWriteCond <= 1;
                @(posedge clk);
                PCWriteCond <= 0;
            end
            // else if (Op ==5'b11111)
            // begin 
            //     repeat (2)@(posedge clk);
            //     PCWriteCond <= 1;
            //     @(posedge clk);
            //     PCWriteCond <= 0;
            // end
            else if (Op == 5'b01100)
            begin
                @(posedge clk);
                PCWriteCond <= 1;
                @(posedge clk);
                PCWriteCond <= 0;
            end
            else if (Op == 5'b01111) begin
                @(posedge clk);
                PCWriteCond <=1;
                @(posedge clk);
                PCWriteCond <= 0;
            end
        
    end
    always @(posedge clk) begin  
    case(Op)  
    5'b01001:
    begin  //LW
        repeat(2)@(posedge clk);
        RegWrite <=1;
        @(posedge clk);
        RegWrite <= 0;
        @(posedge clk);
    end
 5'b01010:
    begin //SW
        //@(posedge clk);
        MemWrite <= 1;
        @(posedge clk);
        MemWrite <= 0;
        @(posedge clk);
    end
 5'b00000,5'b00001,5'b00011,5'b00100: //Rtype
    begin
        @(posedge clk);
        RegWrite <=1;
        @(posedge clk);
        RegWrite <= 0;
        @(posedge clk);
        @(posedge clk);
    end
   5'b00010: //LWS
   begin
        repeat(2)@(posedge clk);
        RegWrite <=1;
        @(posedge clk);
        RegWrite <= 0;
        @(posedge clk);
   end
 5'b01101:
    begin // JAL
        RegWrite <=1;
        @(posedge clk);
        RegWrite <= 0;
    end
    5'b00111,5'b01000:
    begin // ANDI & ADDI
        @(posedge clk);
        RegWrite <=1;
        @(posedge clk);
        RegWrite <= 0;
        @(posedge clk);
    end
    5'b01111: //NOP
    begin
        RegWrite <= 0;
        MemWrite <= 0;
        @(posedge clk);
    end
    5'b01110: //LUI
    begin
        RegWrite <=1;
        @(posedge clk);
        RegWrite <= 0;
        @(posedge clk);
    end
 endcase
        end
    
endmodule

controlUnit.v
module controlUnit (
    input [4:0] Op,
    input [1:0] cond,
    input zeroFlag,
    input branchZero,
    input sf,
    output reg reg2sel,
    output reg[1:0] Mem2Reg,
    output reg MemRead,ALUSrc,
    output reg [1:0] RegDst,
    output [1:0] PCSource,
    output reg [4:0] ALUOp,
    output reg SeSel,
    output reg zeroFlagWrite
);
reg [4:0] temp =0 ;
assign zeroFlagWrite = sf || Op == 5'b00101;
assign PCSource[0] = Op==5'b01100 || Op == 5'b01101 || (Op==5'b01011 & branchZero);
assign PCSource[1] = Op==5'b00110;
always @(*)
    begin
 if(cond == 0 || cond == 1 & zeroFlag == 1 || cond == 2 & zeroFlag == 0) begin
   temp = Op;
 end
 else temp = 5'b01111;
   ALUOp <= temp;
 case(temp)  
5'b01001:
    begin  //LW
    RegDst <=2'b01;
    ALUSrc <= 1;
    MemRead <=1;
    Mem2Reg <=1;
    SeSel <= 1;
    end
 5'b01100:
    begin // J
    MemRead <=0;
    Mem2Reg <=0;
    SeSel <= 0;
    end
 5'b01010:
    begin //SW
    ALUSrc <= 1;
    MemRead <=0;
    reg2sel<=1;
    SeSel <= 1;
    end
  5'b01011: //BEQ
    begin
    ALUSrc <= 0;
    MemRead <=0;
    Mem2Reg <=0;
    SeSel <= 1;
    reg2sel<=1;
    end
 5'b00110:
    begin // JR
    MemRead <=0;
    end
 5'b00000,5'b00001,5'b00011,5'b00100: //Rtype
    begin
    RegDst <=2'b00;
    ALUSrc <= 0;
    MemRead <=0;
    Mem2Reg <=0;
    reg2sel<=0;
    end
   
   5'b00010: begin //LWS
    RegDst <=2'b00;
    ALUSrc <= 0;
    MemRead <=1;
    Mem2Reg <= 1;
    reg2sel<=0;
   end
 5'b01101:
    begin // JAL
    RegDst <=2'b11;
    MemRead <=0;
    Mem2Reg <= 2;
    end
 5'b01110:
    begin // LUI
    RegDst <=2'b10;
    MemRead <=0;
    Mem2Reg <= 3;
    SeSel <= 0;
    end
 5'b00101:
    begin // CMP
    ALUSrc <= 0;
    MemRead <=0;
    Mem2Reg <=0;
    reg2sel<=0;
    end
    5'b00111,5'b01000:
    begin // ANDI & ADDI
    RegDst <=2'b00;
    ALUSrc <= 1;
    MemRead <=0;
    Mem2Reg <=0;
    SeSel <= 1;
    end
    default:
    begin
      ALUOp <= 5'b01111;
      MemRead <= 0;
    end
    
 endcase
        end
    
endmodule

CPU.v
module CPU (
    input clk
);
    wire [23:0] PCin,PCout,ALUOut,PCMuxOut, instruction,Data,instructionBuff,writeData,A,B,ABuff,BBuff,nextPC,nextPCBuff,PCJump,PCJumpBuff,ALUIn,DataOut,SEOut,dataBuff,Result,SEOut1,SEOut2;
    wire [1:0] cond=instructionBuff[1:0];
    wire [4:0] Op= instructionBuff[6:2];
    wire sf,zeroFlag,MemRead,MemWrite,ALUSrc,RegWrite,PCWriteCond,SeSel;
    wire [1:0] Mem2Reg;
    assign sf =instructionBuff[7];
    wire [2:0] Rd,Rs,Rt,writeReg,reg2;
    wire [4:0] ALUOp;
    assign Rd=instructionBuff[10:8];
    assign Rs=instructionBuff[13:11];
    assign Rt=instructionBuff[16:14];
    wire [1:0] RegDst,PCSource;
    controlUnit cu(Op,cond,zero,zeroFlag,sf,reg2sel,Mem2Reg,MemRead,ALUSrc,RegDst,PCSource,ALUOp,SeSel,zeroFlagWrite);
    writeControl WControl(ALUOp,zero,RegWrite,MemWrite,PCWriteCond,clk);
    Adder PCAdd(PCout,24'b1,nextPC);
    Adder PCJumpadd(PCout,SEOut,PCJump);
    Reg PCAddBuffer(nextPC,nextPCBuff,1'b1,clk);
    Reg PCJumpBuffer(PCJump,PCJumpBuff,1'b1,clk);
    Reg PC(PCin,PCout,PCWriteCond,clk);
    Memory instructionMem(PCout,24'bz,instruction,1'b0,1'b1,clk);
    Memory dataMem(ALUOut,BBuff,DataOut,MemWrite,MemRead,clk);
    Reg instructionBuffer(instruction,instructionBuff,1'b1,clk);
    Reg memBuffer(DataOut,dataBuff,1'b1,clk);
    Reg ABuffer(A,ABuff,1'b1,clk);
    Reg BBuffer(B,BBuff,1'b1,clk);
    Mux4x1 wRegMux(RegDst,Rd,Rt,3'b001,3'b111,writeReg);
    Mux4x1 writeDataMux(Mem2Reg,ALUOut,dataBuff,nextPC,SEOut << 7,writeData);
    RegisterFile RegFile(Rs,reg2,writeReg,writeData,A,B,RegWrite,clk);
    Mux2x1 readReg2(reg2sel, Rt, Rd, reg2);

    //Sign Extend
    SignExtend#(17) SE_17Bit(instructionBuff[23:8],1'b1,SEOut1);
    SignExtend#(10) SE_10Bit(instructionBuff[23:14],1'b1,SEOut2);
    Mux2x1 SE(SeSel, SEOut1, SEOut2, SEOut);

    Mux2x1 ALUMux(ALUSrc,BBuff,SEOut,ALUIn);
    ALU alu(ABuff,ALUIn,ALUOp,zeroFlag,Result);
    Reg aluReg(Result,ALUOut,1'b1,clk);
    Mux4x1 nextPCMux(PCSource,nextPCBuff,PCJumpBuff,ABuff,0,PCin);
    Reg statusReg(zeroFlag,zero,zeroFlagWrite,clk);
   
endmodule

testbench.v
`timescale 1ns/1ns
`include "Adder.v"
`include "ALU.v"
`include "Memory.v"
`include "Mux.v"
`include "Reg.v"
`include "RegFile.v"
`include "SignExtend.v"
`include "controlUnit.v"
`include "CPU.v"
`include "writeControl.v"
module testbench (
);
    reg PCWriteCond,PCWrite,MemRead,MemWrite,Mem2Reg,IRWrite,PCSource;
    reg[4:0] ALUOp;
    reg ALUSrc,RegWrite,RegDst,clk;

    CPU cpu(clk);
    initial begin
        clk =0;
    forever begin
        #5 clk = ~clk;
    end
    end
    initial begin
        
        /*
        *int arr[6];
        for (int i=0;i<6;i++) arr[6] = i;
        */
              
        cpu.instructionMem.Mem[0] = 0;
        cpu.instructionMem.Mem[1] = 24'b00000001001011000_01110_00;// LUI R1 = decimal(600) << 7
        cpu.instructionMem.Mem[2] = 24'b0000000110_000_100_0_01000_00; //ADDI R4 = R0 + 6
        cpu.instructionMem.Mem[3] = 24'b0000000000_000_010_0_01000_00; // ADDI R2 = R0 + 0
        //loop1: 
        cpu.instructionMem.Mem[4] = 24'b0000000_010_001_011_0_00011_00;// ADD R3 = R1 + R2
        cpu.instructionMem.Mem[5] = 24'b0000000000_011_010_0_01010_00; // Sw Mem(R3+0) = Reg(R2)
        cpu.instructionMem.Mem[6] = 24'b0000000001_010_010_0_01000_00;// ADDI R2 = R2 + 1
        cpu.instructionMem.Mem[7] = 24'b0000000011_010_100_0_01011_00;// BEQ if (R2 == R4) Jump to A meanning R2 == 6
        cpu.instructionMem.Mem[8] = 24'b0000000100_000_111_0_01000_00;// ADDI R7 = R0 + 4
        cpu.instructionMem.Mem[9] = 24'b0000000_000_111_000_0_00110_00;// JR PC = Reg(R7)
        ////////////////////////////////////////////////////////////////////////////////////////////////////

        ////////////////////////////////////////////////////////////////////////////////////////////////////
        // for (int i=0;i<6;i++) j = arr[i];
        //loop2
        cpu.instructionMem.Mem[10] = 24'b0000000000_000_010_0_01000_00;//ADDI R2 = R0 + 0
        cpu.instructionMem.Mem[11] = 24'b0000000_010_001_101_0_00010_00;// LWS R5 = Mem(Reg(R2)+Reg(R1))
        cpu.instructionMem.Mem[12] = 24'b0000000001_010_010_0_01000_00;// ADDI R2 = R2 + 1
        cpu.instructionMem.Mem[13] = 24'b0000000011_010_100_0_01011_00;//BEQ if (R2 == R4) Jump to A meanning R2 == 6
        cpu.instructionMem.Mem[14] = 24'b0000001011_000_111_0_01000_00;// ADDI R7 = R0 + 11
        cpu.instructionMem.Mem[15] = 24'b0000000_000_111_000_0_00110_00;// JR PC = Reg(R7)
        // cpu.instructionMem.Mem[1] = 24'b0000000_000_001_010_1_00100_00;
        // cpu.instructionMem.Mem[2] = 24'b0000000_000_001_010_1_00011_10;
        // cpu.instructionMem.Mem[1] = 24'b0000000001_000_001_0_01000_00;
        // cpu.instructionMem.Mem[2] = 24'b0000000_001_000_010_0_00011_00;
    end
    initial begin
        $dumpfile("dump.vcd");
        $dumpvars;
        #10000
        $finish;
    end

endmodule

dump.vcd
$date
	Wed Feb 22 19:56:36 2023
$end
$version
	Icarus Verilog
$end
$timescale
	1ns
$end
$scope module testbench $end
$var reg 1 ! clk $end
$scope module cpu $end
$var wire 1 ! clk $end
$var wire 1 " zeroFlagWrite $end
$var wire 1 # zeroFlag $end
$var wire 1 $ zero $end
$var wire 3 % writeReg [2:0] $end
$var wire 24 & writeData [23:0] $end
$var wire 1 ' sf $end
$var wire 1 ( reg2sel $end
$var wire 3 ) reg2 [2:0] $end
$var wire 24 * nextPCBuff [23:0] $end
$var wire 24 + nextPC [23:0] $end
$var wire 24 , instructionBuff [23:0] $end
$var wire 24 - instruction [23:0] $end
$var wire 24 . dataBuff [23:0] $end
$var wire 2 / cond [1:0] $end
$var wire 1 0 SeSel $end
$var wire 24 1 SEOut2 [23:0] $end
$var wire 24 2 SEOut1 [23:0] $end
$var wire 24 3 SEOut [23:0] $end
$var wire 3 4 Rt [2:0] $end
$var wire 3 5 Rs [2:0] $end
$var wire 24 6 Result [23:0] $end
$var wire 1 7 RegWrite $end
$var wire 2 8 RegDst [1:0] $end
$var wire 3 9 Rd [2:0] $end
$var wire 24 : PCout [23:0] $end
$var wire 24 ; PCin [23:0] $end
$var wire 1 < PCWriteCond $end
$var wire 2 = PCSource [1:0] $end
$var wire 24 > PCJumpBuff [23:0] $end
$var wire 24 ? PCJump [23:0] $end
$var wire 5 @ Op [4:0] $end
$var wire 1 A MemWrite $end
$var wire 1 B MemRead $end
$var wire 2 C Mem2Reg [1:0] $end
$var wire 24 D DataOut [23:0] $end
$var wire 24 E BBuff [23:0] $end
$var wire 24 F B [23:0] $end
$var wire 1 G ALUSrc $end
$var wire 24 H ALUOut [23:0] $end
$var wire 5 I ALUOp [4:0] $end
$var wire 24 J ALUIn [23:0] $end
$var wire 24 K ABuff [23:0] $end
$var wire 24 L A [23:0] $end
$scope module ABuffer $end
$var wire 1 ! clk $end
$var wire 1 M write $end
$var wire 24 N in [23:0] $end
$var reg 24 O Register [23:0] $end
$var reg 24 P out [23:0] $end
$upscope $end
$scope module ALUMux $end
$var wire 1 G sel $end
$var wire 24 Q b [23:0] $end
$var wire 24 R a [23:0] $end
$var reg 24 S out [23:0] $end
$upscope $end
$scope module BBuffer $end
$var wire 1 ! clk $end
$var wire 1 T write $end
$var wire 24 U in [23:0] $end
$var reg 24 V Register [23:0] $end
$var reg 24 W out [23:0] $end
$upscope $end
$scope module PC $end
$var wire 1 ! clk $end
$var wire 1 < write $end
$var wire 24 X in [23:0] $end
$var reg 24 Y Register [23:0] $end
$var reg 24 Z out [23:0] $end
$upscope $end
$scope module PCAdd $end
$var wire 24 [ A [23:0] $end
$var wire 24 \ B [23:0] $end
$var wire 24 ] out [23:0] $end
$upscope $end
$scope module PCAddBuffer $end
$var wire 1 ! clk $end
$var wire 24 ^ in [23:0] $end
$var wire 1 _ write $end
$var reg 24 ` Register [23:0] $end
$var reg 24 a out [23:0] $end
$upscope $end
$scope module PCJumpBuffer $end
$var wire 1 ! clk $end
$var wire 1 b write $end
$var wire 24 c in [23:0] $end
$var reg 24 d Register [23:0] $end
$var reg 24 e out [23:0] $end
$upscope $end
$scope module PCJumpadd $end
$var wire 24 f A [23:0] $end
$var wire 24 g out [23:0] $end
$var wire 24 h B [23:0] $end
$upscope $end
$scope module RegFile $end
$var wire 3 i Rdata1 [2:0] $end
$var wire 3 j Rdata2 [2:0] $end
$var wire 3 k WriteReg [2:0] $end
$var wire 1 ! clk $end
$var wire 24 l Wdata [23:0] $end
$var wire 1 7 RegWrite $end
$var reg 24 m Outdata1 [23:0] $end
$var reg 24 n Outdata2 [23:0] $end
$var integer 32 o i [31:0] $end
$upscope $end
$scope module SE $end
$var wire 1 0 sel $end
$var wire 24 p b [23:0] $end
$var wire 24 q a [23:0] $end
$var reg 24 r out [23:0] $end
$upscope $end
$scope module SE_10Bit $end
$var wire 1 s ExtOp $end
$var wire 10 t in [9:0] $end
$var reg 24 u out [23:0] $end
$upscope $end
$scope module SE_17Bit $end
$var wire 1 v ExtOp $end
$var wire 17 w in [16:0] $end
$var reg 24 x out [23:0] $end
$upscope $end
$scope module WControl $end
$var wire 1 ! clk $end
$var wire 1 $ zeroFlag $end
$var wire 5 y Op [4:0] $end
$var reg 1 A MemWrite $end
$var reg 1 < PCWriteCond $end
$var reg 1 7 RegWrite $end
$upscope $end
$scope module alu $end
$var wire 24 z A [23:0] $end
$var wire 24 { B [23:0] $end
$var wire 5 | OP [4:0] $end
$var reg 24 } Result [23:0] $end
$var reg 24 ~ temp [23:0] $end
$var reg 1 # zeroFlag $end
$upscope $end
$scope module aluReg $end
$var wire 1 ! clk $end
$var wire 24 !" in [23:0] $end
$var wire 1 "" write $end
$var reg 24 #" Register [23:0] $end
$var reg 24 $" out [23:0] $end
$upscope $end
$scope module cu $end
$var wire 5 %" Op [4:0] $end
$var wire 1 # branchZero $end
$var wire 2 &" cond [1:0] $end
$var wire 1 ' sf $end
$var wire 1 $ zeroFlag $end
$var wire 1 " zeroFlagWrite $end
$var wire 2 '" PCSource [1:0] $end
$var reg 5 (" ALUOp [4:0] $end
$var reg 1 G ALUSrc $end
$var reg 2 )" Mem2Reg [1:0] $end
$var reg 1 B MemRead $end
$var reg 2 *" RegDst [1:0] $end
$var reg 1 0 SeSel $end
$var reg 1 ( reg2sel $end
$var reg 5 +" temp [4:0] $end
$upscope $end
$scope module dataMem $end
$var wire 24 ," Address [23:0] $end
$var wire 24 -" DataIn [23:0] $end
$var wire 1 B MemR $end
$var wire 1 A MemW $end
$var wire 1 ! clk $end
$var wire 24 ." DataOut [23:0] $end
$var integer 32 /" i [31:0] $end
$upscope $end
$scope module instructionBuffer $end
$var wire 1 ! clk $end
$var wire 1 0" write $end
$var wire 24 1" in [23:0] $end
$var reg 24 2" Register [23:0] $end
$var reg 24 3" out [23:0] $end
$upscope $end
$scope module instructionMem $end
$var wire 24 4" Address [23:0] $end
$var wire 24 5" DataIn [23:0] $end
$var wire 24 6" DataOut [23:0] $end
$var wire 1 7" MemR $end
$var wire 1 8" MemW $end
$var wire 1 ! clk $end
$var integer 32 9" i [31:0] $end
$upscope $end
$scope module memBuffer $end
$var wire 1 ! clk $end
$var wire 24 :" in [23:0] $end
$var wire 1 ;" write $end
$var reg 24 <" Register [23:0] $end
$var reg 24 =" out [23:0] $end
$upscope $end
$scope module nextPCMux $end
$var wire 24 >" a [23:0] $end
$var wire 24 ?" b [23:0] $end
$var wire 24 @" c [23:0] $end
$var wire 24 A" d [23:0] $end
$var wire 2 B" sel [1:0] $end
$var reg 24 C" out [23:0] $end
$upscope $end
$scope module readReg2 $end
$var wire 24 D" a [23:0] $end
$var wire 24 E" b [23:0] $end
$var wire 1 ( sel $end
$var reg 24 F" out [23:0] $end
$upscope $end
$scope module statusReg $end
$var wire 1 ! clk $end
$var wire 24 G" in [23:0] $end
$var wire 1 " write $end
$var reg 24 H" Register [23:0] $end
$var reg 24 I" out [23:0] $end
$upscope $end
$scope module wRegMux $end
$var wire 24 J" a [23:0] $end
$var wire 24 K" b [23:0] $end
$var wire 24 L" c [23:0] $end
$var wire 24 M" d [23:0] $end
$var wire 2 N" sel [1:0] $end
$var reg 24 O" out [23:0] $end
$upscope $end
$scope module writeDataMux $end
$var wire 24 P" a [23:0] $end
$var wire 24 Q" b [23:0] $end
$var wire 24 R" c [23:0] $end
$var wire 24 S" d [23:0] $end
$var wire 2 T" sel [1:0] $end
$var reg 24 U" out [23:0] $end
$upscope $end
$upscope $end
$upscope $end
$enddefinitions $end
#0
$dumpvars
b0 U"
b0 T"
b0 S"
b1 R"
b0 Q"
b0 P"
b0 O"
b0 N"
b111 M"
b1 L"
b0 K"
b0 J"
b0 I"
b0 H"
b1 G"
b0 F"
b0 E"
b0 D"
b0 C"
b0 B"
b0 A"
b0 @"
b0 ?"
b0 >"
b0 ="
b0 <"
1;"
b0 :"
b1000000000000000000000000 9"
08"
17"
b0 6"
bz 5"
b0 4"
b0 3"
b0 2"
b0 1"
10"
b1000000000000000000000000 /"
b0 ."
b0 -"
b0 ,"
b0 +"
b0 *"
b0 )"
b0 ("
b0 '"
b0 &"
b0 %"
b0 $"
b0 #"
1""
b0 !"
b0 ~
b0 }
b0 |
b0 {
b0 z
b0 y
b0 x
b0 w
1v
b0 u
b0 t
1s
b0 r
b0 q
b0 p
b1000 o
b0 n
b0 m
b0 l
b0 k
b0 j
b0 i
b0 h
b0 g
b0 f
b0 e
b0 d
b0 c
1b
b0 a
b0 `
1_
b1 ^
b1 ]
b1 \
b0 [
b0 Z
b0 Y
b0 X
b0 W
b0 V
b0 U
1T
b0 S
b0 R
b0 Q
b0 P
b0 O
b0 N
1M
b0 L
b0 K
b0 J
b0 I
b0 H
0G
b0 F
b0 E
b0 D
b0 C
0B
xA
b0 @
b0 ?
b0 >
b0 =
x<
b0 ;
b0 :
b0 9
b0 8
x7
b0 6
b0 5
b0 4
b0 3
b0 2
b0 1
x0
b0 /
b0 .
b0 -
b0 ,
b1 +
b0 *
b0 )
0(
0'
b0 &
b0 %
0$
1#
0"
0!
$end
#5
b1 ;
b1 X
b1 C"
b1 *
b1 a
b1 >"
b1 `
1!
#10
0!
#15
17
1!
#20
0!
#25
1<
07
1!
#30
0!
#35
b10 +
b10 ]
b10 ^
b10 R"
b1 ?
b1 c
b1 g
b10010110000111000 -
b10010110000111000 1"
b10010110000111000 6"
b1 :
b1 Z
b1 [
b1 f
b1 4"
b1 Y
0<
1!
#40
0!
#45
b1001011000000000 &
b1001011000000000 l
b1001011000000000 U"
b1001011000000000 S"
b100101101 ?
b100101101 c
b100101101 g
b100101100 3
b100101100 Q
b100101100 h
b100101100 r
b1 %
b1 k
b100 )
b100 j
b100 1
b100 p
b100 u
b100101100 2
b100101100 q
b100101100 x
b1 O"
b100 F"
00
b11 C
b11 )"
b11 T"
b10 8
b10 *"
b10 N"
b1110 I
b1110 y
b1110 |
b1110 ("
b10 ;
b10 X
b10 C"
b1110 +"
b100 t
b100101100 w
b100 K"
b100 D"
b100 4
b101 5
b101 i
b100 J"
b100 E"
b100 9
b1110 @
b1110 %"
b10 *
b10 a
b10 >"
b1 >
b1 e
b1 ?"
b10010110000111000 ,
b10010110000111000 3"
b10 `
b1 d
b10010110000111000 2"
1!
#50
0!
#55
b100101101 >
b100101101 e
b100101101 ?"
b100101101 d
17
1<
1!
#60
0!
#65
b11 +
b11 ]
b11 ^
b11 R"
b100101110 ?
b100101110 c
b100101110 g
b11000010000100000 -
b11000010000100000 1"
b11000010000100000 6"
b10 :
b10 Z
b10 [
b10 f
b10 4"
0<
07
b10 Y
1!
#70
0!
#75
b0 G"
0#
b110 6
b110 }
b110 !"
b1100000000 S"
b110 ~
b100 %
b100 k
b1000 ?
b1000 c
b1000 g
b110 3
b110 Q
b110 h
b110 r
b0 &
b0 l
b0 U"
b110 J
b110 S
b110 {
b100 O"
b110 )
b110 j
b110 1
b110 p
b110 u
b110000100 2
b110000100 q
b110000100 x
b110 F"
10
b0 C
b0 )"
b0 T"
1G
b0 8
b0 *"
b0 N"
b1000 I
b1000 y
b1000 |
b1000 ("
b11 ;
b11 X
b11 C"
b1000 +"
b110 t
b110000100 w
b110 K"
b110 D"
b110 4
b0 5
b0 i
b1000 @
b1000 %"
b11000010000100000 ,
b11000010000100000 3"
b100101110 >
b100101110 e
b100101110 ?"
b11 *
b11 a
b11 >"
b11000010000100000 2"
b100101110 d
b11 `
1!
#80
0!
#85
b110 &
b110 l
b110 U"
b1000 >
b1000 e
b1000 ?"
b110 H
b110 $"
b110 ,"
b110 P"
b1000 d
b110 #"
1!
#90
0!
#95
1<
17
1!
#100
0!
#105
b100 +
b100 ]
b100 ^
b100 R"
b1001 ?
b1001 c
b1001 g
b1000100000 -
b1000100000 1"
b1000100000 6"
b11 :
b11 Z
b11 [
b11 f
b11 4"
07
b11 Y
0<
1!
#110
0!
#115
b1 G"
1#
b0 6
b0 }
b0 !"
b0 ~
b0 J
b0 S
b0 {
b0 S"
b11 ?
b11 c
b11 g
b0 3
b0 Q
b0 h
b0 r
b10 %
b10 k
b0 )
b0 j
b0 1
b0 p
b0 u
b10 2
b10 q
b10 x
b10 O"
b0 F"
b100 ;
b100 X
b100 C"
b0 t
b10 w
b0 K"
b0 D"
b0 4
b10 J"
b10 E"
b10 9
b1000100000 ,
b1000100000 3"
b1001 >
b1001 e
b1001 ?"
b100 *
b100 a
b100 >"
b1000100000 2"
b1001 d
b100 `
1!
#120
0!
#125
b0 &
b0 l
b0 U"
b11 >
b11 e
b11 ?"
b0 H
b0 $"
b0 ,"
b0 P"
b11 d
b0 #"
1!
#130
0!
#135
1<
17
1!
#140
0!
#145
b101 +
b101 ]
b101 ^
b101 R"
b100 ?
b100 c
b100 g
b1000101100001100 -
b1000101100001100 1"
b1000101100001100 6"
b100 :
b100 Z
b100 [
b100 f
b100 4"
07
b100 Y
0<
1!
#150
0!
#155
b100000000 S"
b110 ?
b110 c
b110 g
b10 3
b10 Q
b10 h
b10 r
b11 %
b11 k
b10 )
b10 j
b10 1
b10 p
b10 u
b10001011 2
b10001011 q
b10001011 x
b1001011000000000 L
b1001011000000000 N
b1001011000000000 m
b11 O"
b10 F"
0G
b11 I
b11 y
b11 |
b11 ("
b101 ;
b101 X
b101 C"
b11 +"
b10 t
b10001011 w
b10 K"
b10 D"
b10 4
b1 5
b1 i
b11 J"
b11 E"
b11 9
b11 @
b11 %"
b1000101100001100 ,
b1000101100001100 3"
b100 >
b100 e
b100 ?"
b101 *
b101 a
b101 >"
b1000101100001100 2"
b100 d
b101 `
1!
#160
0!
#165
b0 G"
0#
b1001011000000000 6
b1001011000000000 }
b1001011000000000 !"
b1001011000000000 ~
b110 >
b110 e
b110 ?"
b1001011000000000 K
b1001011000000000 P
b1001011000000000 z
b1001011000000000 @"
b110 d
b1001011000000000 O
1!
#170
0!
#175
b1001011000000000 &
b1001011000000000 l
b1001011000000000 U"
b1001011000000000 H
b1001011000000000 $"
b1001011000000000 ,"
b1001011000000000 P"
1<
b1001011000000000 #"
17
1!
#180
0!
#185
b110 +
b110 ]
b110 ^
b110 R"
b111 ?
b111 c
b111 g
b1101000101000 -
b1101000101000 1"
b1101000101000 6"
b101 :
b101 Z
b101 [
b101 f
b101 4"
07
b101 Y
0<
1!
#190
0!
#195
b1001011000000000 6
b1001011000000000 }
b1001011000000000 !"
b0 S"
b1001011000000000 ~
b101 ?
b101 c
b101 g
b0 3
b0 Q
b0 h
b0 r
b0 J
b0 S
b0 {
b10 %
b10 k
b10 )
b10 j
b0 1
b0 p
b0 u
b11010 2
b11010 q
b11010 x
b10 O"
b10 F"
1(
1G
b1010 I
b1010 y
b1010 |
b1010 ("
b110 ;
b110 X
b110 C"
b1010 +"
b0 t
b11010 w
b0 K"
b0 D"
b0 4
b11 5
b11 i
b10 J"
b10 E"
b10 9
b1010 @
b1010 %"
b1101000101000 ,
b1101000101000 3"
b111 >
b111 e
b111 ?"
b110 *
b110 a
b110 >"
b1101000101000 2"
b111 d
b110 `
1!
#200
0!
#205
b101 >
b101 e
b101 ?"
b101 d
1!
#210
0!
#215
1<
1A
1!
#220
0!
#225
b111 +
b111 ]
b111 ^
b111 R"
b110 ?
b110 c
b110 g
b101001000100000 -
b101001000100000 1"
b101001000100000 6"
b110 :
b110 Z
b110 [
b110 f
b110 4"
0A
b110 Y
0<
1!
#230
0!
